pyforth/__init__.py
pyforth-1.2.0.dist-info/licenses/LICENSE
pyforth-1.2.0.dist-info/METADATA
pyforth-1.2.0.dist-info/WHEEL
pyforth-1.2.0.dist-info/top_level.txt
pyforth-1.2.0.dist-info/RECORD
