Metadata-Version: 2.4
Name: pyforth
Version: 1.2.0
Summary: A minimalistic, Python-based Forth+ interpreter
Author: UndrDsk0M
License: MIT License
Project-URL: Homepage, https://github.com/UndrDsk0M/PyForth
Project-URL: Repository, https://github.com/UndrDsk0M/PyForth
Requires-Python: >=3.7
License-File: LICENSE
Dynamic: license-file
